django_distill/__init__.py
django_distill/distill.py
django_distill/errors.py
django_distill/publisher.py
django_distill/renderer.py
django_distill/backends/__init__.py
django_distill/backends/amazon_s3.py
django_distill/backends/google_storage.py
django_distill/backends/rackspace_files.py
django_distill/management/__init__.py
django_distill/management/commands/__init__.py
django_distill/management/commands/distill-local.py
django_distill/management/commands/distill-publish.py
django_distill/management/commands/distill-test-publish.py
tests/__init__.py
tests/settings.py
tests/test_interface.py
tests/test_renderer.py
tests/urls.py
django_distill-2.1.dist-info/LICENSE
django_distill-2.1.dist-info/METADATA
django_distill-2.1.dist-info/WHEEL
django_distill-2.1.dist-info/top_level.txt
django_distill-2.1.dist-info/RECORD
